formula/__init__.py
formula/_formula.pypy39-pp73-win_amd64.pyd
formula/formula.py
tests/__init__.py
tests/test_operations.py
tests/test_simple.py
formula-4.0.3.dist-info/LICENSE
formula-4.0.3.dist-info/METADATA
formula-4.0.3.dist-info/WHEEL
formula-4.0.3.dist-info/top_level.txt
formula-4.0.3.dist-info/RECORD
