Metadata-Version: 2.1
Name: formula
Version: 4.0.3
Summary: Arbitrary-precision formula parser and solver.
Home-page: https://github.com/hozblok/formula
Author: Ivan Ergunov
Author-email: hozblok@gmail.com
License: Apache-2.0
Classifier: Development Status :: 5 - Production/Stable
Classifier: License :: OSI Approved :: Apache Software License
Classifier: Operating System :: OS Independent
Classifier: Programming Language :: C++
Classifier: Programming Language :: Python
Classifier: Topic :: Scientific/Engineering :: Mathematics
Classifier: Topic :: Scientific/Engineering :: Physics
Requires-Python: >=3.6, <4
License-File: LICENSE
Requires-Dist: pybind11>=2.6
Provides-Extra: test
Requires-Dist: pytest; extra == "test"
